.coveragerc
.travis.yml
COPYING
DESCRIPTION.rst
MANIFEST.in
Makefile
README.md
pip.conf
requirements-dev.txt
setup.cfg
setup.py
tox.ini
flake8_import_style/__init__.py
flake8_import_style.egg-info/PKG-INFO
flake8_import_style.egg-info/SOURCES.txt
flake8_import_style.egg-info/dependency_links.txt
flake8_import_style.egg-info/entry_points.txt
flake8_import_style.egg-info/requires.txt
flake8_import_style.egg-info/top_level.txt
flake8_import_style/tests/__init__.py